.coveragerc
LICENSE.txt
MANIFEST.in
README.md
pytest.ini
requirements.txt
setup.cfg
setup.py
src/plt_pack/__init__.py
src/plt_pack/__version.py
src/plt_pack/msgpack_import.py
src/plt_pack/utils.py
src/plt_pack.egg-info/PKG-INFO
src/plt_pack.egg-info/SOURCES.txt
src/plt_pack.egg-info/dependency_links.txt
src/plt_pack.egg-info/requires.txt
src/plt_pack.egg-info/top_level.txt
src/plt_pack/file/__init__.py
src/plt_pack/file/file_dict.py
src/plt_pack/file/metadata.py
src/plt_pack/file/misc.py
src/plt_pack/file/plt_file.py
src/plt_pack/file/save_read.py
src/plt_pack/jupyter_support/__init__.py
src/plt_pack/jupyter_support/create_cell.py
src/plt_pack/jupyter_support/jupyter_code.py
src/plt_pack/parse/__init__.py
src/plt_pack/parse/check_used_globals.py
src/plt_pack/parse/check_version.py
src/plt_pack/parse/func_dict.py
src/plt_pack/parse/func_parser.py
src/plt_pack/parse/get_source_code.py
src/plt_pack/parse/parse_func_name.py
src/plt_pack/project_utils/__init__.py
src/plt_pack/project_utils/plt_project.py
src/plt_pack/project_utils/save_opts.py